datasette_events_db/__init__.py
datasette_events_db-0.1a2.dist-info/licenses/LICENSE
datasette_events_db-0.1a2.dist-info/METADATA
datasette_events_db-0.1a2.dist-info/WHEEL
datasette_events_db-0.1a2.dist-info/entry_points.txt
datasette_events_db-0.1a2.dist-info/top_level.txt
datasette_events_db-0.1a2.dist-info/RECORD
