Metadata-Version: 2.4
Name: datasette-events-db
Version: 0.1a2
Summary: Log Datasette events to a database table
Author: Simon Willison
License-Expression: Apache-2.0
Project-URL: Homepage, https://github.com/datasette/datasette-events-db
Project-URL: Changelog, https://github.com/datasette/datasette-events-db/releases
Project-URL: Issues, https://github.com/datasette/datasette-events-db/issues
Project-URL: CI, https://github.com/datasette/datasette-events-db/actions
Classifier: Framework :: Datasette
Requires-Python: >=3.10
License-File: LICENSE
Requires-Dist: datasette>=1.0a21
Provides-Extra: test
Requires-Dist: pytest; extra == "test"
Requires-Dist: pytest-asyncio; extra == "test"
Dynamic: license-file
